cosmax/__init__.py
cosmax/interpolation/__init__.py
cosmax/interpolation/bilinear.py
cosmax/mass_assignment/__init__.py
cosmax/mass_assignment/cic.py
cosmax/mass_assignment/nearest_neighbour.py
cosmax/nn/fno/__init__.py
cosmax/nn/fno/fno.py
cosmax/nn/fno/fourier_layer.py
cosmax/nn/fno/sequential_fno.py
cosmax/nn/fno/spectral_convolution.py
cosmax/spectral_ops/__init__.py
cosmax/spectral_ops/generator.py
cosmax/spectral_ops/potential.py
cosmax/spectral_ops/power_spectrum.py
cosmax/spectral_ops/spectral_loss.py
cosmax/spectral_ops/spectral_op.py
cosmax/tools/__init__.py
cosmax/tools/fit_field.py
cosmax/tools/gradient.py
cosmax/tools/helpers.py
cosmax-0.0.7.dist-info/METADATA
cosmax-0.0.7.dist-info/WHEEL
cosmax-0.0.7.dist-info/licenses/LICENSE
cosmax-0.0.7.dist-info/RECORD
