Metadata-Version: 2.4
Name: cosmax
Version: 0.0.7
Summary: Fast and differentiable implementations of operations needed for inference and analysis in cosmology. Powered by JAX
Project-URL: Homepage, https://andrinr.github.io/cosmax/
Project-URL: Issues, https://github.com/andrinr/cosmax/issues
Author-email: Andrin Rehmann <andrinrehmann@gmail.com>
License-File: LICENSE
Classifier: License :: OSI Approved :: MIT License
Classifier: Operating System :: OS Independent
Classifier: Programming Language :: Python :: 3
Requires-Python: >=3.8
Requires-Dist: jax>=0.4.0
Requires-Dist: optax>=0.2.0
